setup.py
bin/git_credit
git_credit/__init__.py
git_credit/base.py
git_credit/graph_output.py
git_credit.egg-info/PKG-INFO
git_credit.egg-info/SOURCES.txt
git_credit.egg-info/dependency_links.txt
git_credit.egg-info/requires.txt
git_credit.egg-info/top_level.txt
test/test_base.py