Metadata-Version: 1.1
Name: git-credit
Version: 0.0.6
Summary: A pretty way to show committer stats for git repos
Home-page: https://github.com/a-tal/git_credit
Author: Adam Talsma
Author-email: adam@talsma.ca
License: BSD
Download-URL: https://github.com/a-tal/git_credit
Platform: UNKNOWN
Classifier: Development Status :: 4 - Beta
Classifier: Environment :: Console
Classifier: Intended Audience :: System Administrators
Classifier: License :: OSI Approved :: BSD License
Classifier: Operating System :: POSIX :: Linux
Classifier: Programming Language :: Python
